{"speech":[
{"Speaker_Name":"Speaker1","SpeechTime":15,"Similarity":73,"SpeechStart":0,"ID":0,"SpeechEnd":15},
{"Speaker_Name":"Speaker2","SpeechTime":15,"Similarity":68,"SpeechStart":15,"ID":1,"SpeechEnd":30},
{"Speaker_Name":"Speaker1","SpeechTime":15,"Similarity":67,"SpeechStart":30,"ID":2,"SpeechEnd":45},
{"Speaker_Name":"Speaker3","SpeechTime":15,"Similarity":72,"SpeechStart":45,"ID":3,"SpeechEnd":60},
{"Speaker_Name":"Speaker1","SpeechTime":15,"Similarity":75,"SpeechStart":60,"ID":4,"SpeechEnd":75},
{"Speaker_Name":"Speaker4","SpeechTime":15,"Similarity":74,"SpeechStart":75,"ID":5,"SpeechEnd":90},
{"Speaker_Name":"Speaker1","SpeechTime":15,"Similarity":73,"SpeechStart":90,"ID":6,"SpeechEnd":105},
{"Speaker_Name":"Speaker2","SpeechTime":15,"Similarity":72,"SpeechStart":105,"ID":7,"SpeechEnd":120},
{"Speaker_Name":"Speaker1","SpeechTime":15,"Similarity":70,"SpeechStart":120,"ID":8,"SpeechEnd":135},
{"Speaker_Name":"Speaker3","SpeechTime":15,"Similarity":69,"SpeechStart":135,"ID":9,"SpeechEnd":150},
{"Speaker_Name":"Speaker1","SpeechTime":15,"Similarity":69,"SpeechStart":150,"ID":10,"SpeechEnd":165},
{"Speaker_Name":"Speaker4","SpeechTime":15,"Similarity":68,"SpeechStart":165,"ID":11,"SpeechEnd":180},
{"Speaker_Name":"Speaker1","SpeechTime":15,"Similarity":66,"SpeechStart":180,"ID":12,"SpeechEnd":195},
{"Speaker_Name":"Speaker5","SpeechTime":15,"Similarity":73,"SpeechStart":195,"ID":13,"SpeechEnd":210},
{"Speaker_Name":"Speaker1","SpeechTime":15,"Similarity":68,"SpeechStart":210,"ID":14,"SpeechEnd":225},
{"Speaker_Name":"Speaker5","SpeechTime":15,"Similarity":67,"SpeechStart":225,"ID":15,"SpeechEnd":240},
{"Speaker_Name":"Speaker6","SpeechTime":15,"Similarity":72,"SpeechStart":240,"ID":16,"SpeechEnd":255},
{"Speaker_Name":"Speaker5","SpeechTime":15,"Similarity":75,"SpeechStart":255,"ID":17,"SpeechEnd":270},
{"Speaker_Name":"Speaker7","SpeechTime":15,"Similarity":74,"SpeechStart":270,"ID":18,"SpeechEnd":285},
{"Speaker_Name":"Speaker5","SpeechTime":15,"Similarity":73,"SpeechStart":285,"ID":19,"SpeechEnd":300},
{"Speaker_Name":"Speaker8","SpeechTime":15,"Similarity":72,"SpeechStart":300,"ID":20,"SpeechEnd":315},
{"Speaker_Name":"Speaker5","SpeechTime":15,"Similarity":70,"SpeechStart":315,"ID":21,"SpeechEnd":330},
{"Speaker_Name":"Speaker2","SpeechTime":15,"Similarity":69,"SpeechStart":330,"ID":22,"SpeechEnd":345},
{"Speaker_Name":"Speaker5","SpeechTime":15,"Similarity":69,"SpeechStart":345,"ID":23,"SpeechEnd":360},
{"Speaker_Name":"Speaker3","SpeechTime":15,"Similarity":68,"SpeechStart":360,"ID":24,"SpeechEnd":375},
{"Speaker_Name":"Speaker5","SpeechTime":15,"Similarity":66,"SpeechStart":375,"ID":25,"SpeechEnd":390},
{"Speaker_Name":"Speaker3","SpeechTime":15,"Similarity":68,"SpeechStart":390,"ID":26,"SpeechEnd":405},
{"Speaker_Name":"Speaker1","SpeechTime":15,"Similarity":68,"SpeechStart":405,"ID":27,"SpeechEnd":420}
]}